{
  "_id": "b01bb85f0dd2ccfa",
  "name": "5. A Glimmer of Hope",
  "pages": [
    {
      "_id": "45d5606ef682f4dd",
      "name": "Read to the Players",
      "type": "text",
      "title": {
        "show": true,
        "level": 1
      },
      "text": {
        "format": 1,
        "content": "<p><em>(For runners who ride the relief-camp bus in — selected at the interview, or boarding directly.)</em></p>\n       <blockquote><p>The bus grinds out through the Barrens for hours, no air conditioning, windows that won't open, packed with the desperate and the smell of them. At last a loudspeaker crackles: \"Hope Relief Camp ahead — remain seated.\" Through the front glass you see it: a fenced compound of barracks with bullet-scarred walls and big domed gates. The bus stops. Security guards in clean white step up to escort the new arrivals off.</p></blockquote>\n       <p>(Paraphrased; full boxed text on p.21.)</p>"
      },
      "image": {},
      "video": {
        "controls": true,
        "volume": 0.5
      },
      "src": null,
      "system": {},
      "sort": 0,
      "ownership": {
        "default": -1
      },
      "flags": {},
      "_stats": {
        "coreVersion": "13.351",
        "systemId": "sr2e",
        "systemVersion": "0.1.0",
        "createdTime": 1781600000000,
        "modifiedTime": 1781600000000,
        "lastModifiedBy": null,
        "compendiumSource": null,
        "duplicateSource": null,
        "exportSource": null
      }
    },
    {
      "_id": "54f26fe0205f0c1f",
      "name": "The Ride In",
      "type": "text",
      "title": {
        "show": true,
        "level": 1
      },
      "text": {
        "format": 1,
        "content": "<p>The bus to the camp leaves the enrollment center about <strong>three hours</strong> after the interview — miss it and the team waits for the next one (a good moment to run the Legwork). The ride is miserable: no AC, sealed windows, brutal heat and stench. Unless a character has olfactory protection, call for periodic <strong>Body (4) Tests</strong> to avoid getting sick.</p>"
      },
      "image": {},
      "video": {
        "controls": true,
        "volume": 0.5
      },
      "src": null,
      "system": {},
      "sort": 0,
      "ownership": {
        "default": -1
      },
      "flags": {},
      "_stats": {
        "coreVersion": "13.351",
        "systemId": "sr2e",
        "systemVersion": "0.1.0",
        "createdTime": 1781600000000,
        "modifiedTime": 1781600000000,
        "lastModifiedBy": null,
        "compendiumSource": null,
        "duplicateSource": null,
        "exportSource": null
      }
    },
    {
      "_id": "dbf0b394af1ad856",
      "name": "The Gate Search (the infiltration crux)",
      "type": "text",
      "title": {
        "show": true,
        "level": 1
      },
      "text": {
        "format": 1,
        "content": "<p>The bus parks just inside the main gates and everyone is asked to step off. Camp security — <strong>\"peace-enforcement officers\" (PEOs)</strong> — spend about an hour searching the new arrivals: hands through personal belongings, scanners for weapons and contraband, and metal detectors that flag <em>cyberware</em> (which Project Hope quietly records). Use the <strong>Peace-Enforcement Officer (PEO)</strong> stat block in the Cast — and note that most PEOs are flesh-form soldier ant spirits in human guise.</p>\n       <p><strong>This is the scene's real challenge.</strong> Smuggling something past the search is a runner's Quickness (Palming/Stealth) against the guards' <strong>Perception Test</strong> and scanners. Anything detected is confiscated; the team isn't arrested, just disarmed and noted. Clever stashing, an outside cache, or simply going in clean are the ways through.</p>\n       <p><strong>The perimeter.</strong> The whole camp is ringed by an <strong>8 m chain-link fence topped with three strands of razorwire</strong>, electrified for a <strong>14S</strong> shock to anyone who touches it (and no way to tell from ten metres out that it's live). The fence is <strong>Barrier Rating 24</strong> against vehicles and the like. The party line is that it keeps Glow City's gangs out; really it keeps the \"guests\" in.</p>\n       <p><em>Legal note for color: a warrantless search would be illegal in the UCAS, but the moment an applicant steps through the gate they're on Project Hope's land and \"agree\" to its rules. The camp isn't truly extraterritorial — the guards simply act as if it is, and the desperate don't argue.</em></p>"
      },
      "image": {},
      "video": {
        "controls": true,
        "volume": 0.5
      },
      "src": null,
      "system": {},
      "sort": 0,
      "ownership": {
        "default": -1
      },
      "flags": {},
      "_stats": {
        "coreVersion": "13.351",
        "systemId": "sr2e",
        "systemVersion": "0.1.0",
        "createdTime": 1781600000000,
        "modifiedTime": 1781600000000,
        "lastModifiedBy": null,
        "compendiumSource": null,
        "duplicateSource": null,
        "exportSource": null
      }
    },
    {
      "_id": "b8865474f0d256d4",
      "name": "Behind the Scenes & Debugging",
      "type": "text",
      "title": {
        "show": true,
        "level": 1
      },
      "text": {
        "format": 1,
        "content": "<p>Getting in is supposed to cost the team its firepower — that tension (infiltrators, disarmed, deep in hostile territory) is the point of the camp arc. Don't soften the search, but do reward genuinely clever smuggling or a decker/rigger who arranges an outside cache.</p>\n       <p>If the team tries to fight their way past the gate, they reveal themselves far too early; treat it as a failed infiltration (active alert, the camp's full security responds) rather than a winnable stand-up fight, and steer toward escape and a different approach.</p>"
      },
      "image": {},
      "video": {
        "controls": true,
        "volume": 0.5
      },
      "src": null,
      "system": {},
      "sort": 0,
      "ownership": {
        "default": -1
      },
      "flags": {},
      "_stats": {
        "coreVersion": "13.351",
        "systemId": "sr2e",
        "systemVersion": "0.1.0",
        "createdTime": 1781600000000,
        "modifiedTime": 1781600000000,
        "lastModifiedBy": null,
        "compendiumSource": null,
        "duplicateSource": null,
        "exportSource": null
      }
    }
  ],
  "folder": null,
  "sort": 0,
  "flags": {},
  "ownership": {
    "default": 0
  },
  "_stats": {
    "coreVersion": "13.351",
    "systemId": "sr2e",
    "systemVersion": "0.1.0",
    "createdTime": 1781600000000,
    "modifiedTime": 1781600000000,
    "lastModifiedBy": null,
    "compendiumSource": null,
    "duplicateSource": null,
    "exportSource": null
  },
  "_key": "!journal!b01bb85f0dd2ccfa"
}
